otelserver/__about__.py
otelserver/__init__.py
otel_grpc_server-0.0.2.dist-info/METADATA
otel_grpc_server-0.0.2.dist-info/WHEEL
otel_grpc_server-0.0.2.dist-info/licenses/LICENSE.txt
otel_grpc_server-0.0.2.dist-info/RECORD
