Metadata-Version: 2.1
Name: otel-grpc-server
Version: 0.0.2
Project-URL: Documentation, https://github.com/unknown/otel-grpc-server#readme
Project-URL: Issues, https://github.com/unknown/otel-grpc-server/issues
Project-URL: Source, https://github.com/unknown/otel-grpc-server
Author-email: Pablo Collins <pcollins@splunk.com>
License-Expression: MIT
License-File: LICENSE.txt
Classifier: Development Status :: 4 - Beta
Classifier: Programming Language :: Python
Classifier: Programming Language :: Python :: 3.7
Classifier: Programming Language :: Python :: 3.8
Classifier: Programming Language :: Python :: 3.9
Classifier: Programming Language :: Python :: 3.10
Classifier: Programming Language :: Python :: 3.11
Classifier: Programming Language :: Python :: Implementation :: CPython
Classifier: Programming Language :: Python :: Implementation :: PyPy
Requires-Python: >=3.7
Requires-Dist: grpcio
Requires-Dist: opentelemetry-proto
